py_sod_metrics/__init__.py
py_sod_metrics/fmeasurev2.py
py_sod_metrics/multiscale_iou.py
py_sod_metrics/size_invariance.py
py_sod_metrics/sod_metrics.py
py_sod_metrics/utils.py
pysodmetrics-1.5.1.dist-info/licenses/LICENSE
pysodmetrics-1.5.1.dist-info/METADATA
pysodmetrics-1.5.1.dist-info/WHEEL
pysodmetrics-1.5.1.dist-info/top_level.txt
pysodmetrics-1.5.1.dist-info/RECORD
