Metadata-Version: 2.4
Name: pysodmetrics
Version: 1.5.1
Summary: A simple and efficient metric implementation for grayscale/binary image segmentation like salient object detection, camouflaged object detection, and medical image segmentation.
Author-email: lartpang <lartpang@gmail.com>
Maintainer-email: lartpang <lartpang@gmail.com>
License: MIT License
Project-URL: Homepage, https://github.com/lartpang/PySODMetrics
Project-URL: Documentation, https://github.com/lartpang/PySODMetrics
Project-URL: Repository, https://github.com/lartpang/PySODMetrics.git
Project-URL: Bug Tracker, https://github.com/lartpang/PySODMetrics/issues
Project-URL: Changelog, https://github.com/lartpang/PySODMetrics/blob/master/CHANGELOG.md
Keywords: salient object detection,camouflaged object detection,medical image segmentation,dichotomous image segmentation,saliency detection,metric,deep learning
Classifier: Development Status :: 5 - Production/Stable
Classifier: Environment :: Console
Classifier: Intended Audience :: Developers
Classifier: Operating System :: OS Independent
Classifier: Programming Language :: Python
Classifier: Topic :: Scientific/Engineering :: Artificial Intelligence
Requires-Python: >=3.6
License-File: LICENSE
Requires-Dist: numpy<2.0,>=1.18
Requires-Dist: scipy<2.0,>=1.5
Requires-Dist: scikit-image<0.25,>=0.19
Requires-Dist: opencv-python-headless<5.0.0,>=4.7.0
Dynamic: license-file
